[
null,
{"id":1,"expanded":true,"name":"正門広場","order":31,"parentId":2,"scrollX":565.1999999999999,"scrollY":667.8},
{"id":2,"expanded":true,"name":"ドイツ（フォン企業）","order":30,"parentId":36,"scrollX":442.79999999999995,"scrollY":322.2},
{"id":3,"expanded":true,"name":"本館","order":32,"parentId":1,"scrollX":555.6,"scrollY":423},
{"id":4,"expanded":false,"name":"左本館","order":33,"parentId":3,"scrollX":442.79999999999995,"scrollY":390.59999999999997},
{"id":5,"expanded":false,"name":"右本館","order":34,"parentId":3,"scrollX":442.79999999999995,"scrollY":390.59999999999997},
{"id":6,"expanded":false,"name":"本館2階","order":35,"parentId":3,"scrollX":565.1999999999999,"scrollY":565.8},
{"id":7,"expanded":false,"name":"本館地下","order":36,"parentId":3,"scrollX":722.4,"scrollY":993},
{"id":8,"expanded":false,"name":"マレフィー側","order":40,"parentId":2,"scrollX":748.8,"scrollY":453},
{"id":9,"expanded":true,"name":"ゲオルクの研究所","order":37,"parentId":1,"scrollX":592.8,"scrollY":906.5999999999999},
{"id":10,"expanded":true,"name":"メフィストの研究所","order":38,"parentId":9,"scrollX":1048.8,"scrollY":1210.2},
{"id":11,"expanded":true,"name":"クエスト処理","order":1,"parentId":0,"scrollX":442.79999999999995,"scrollY":322.2},
{"id":12,"expanded":false,"name":"開始時","order":6,"parentId":11,"scrollX":593.25,"scrollY":440.25},
{"id":13,"expanded":true,"name":"リザルト","order":7,"parentId":11,"scrollX":737.25,"scrollY":452.25},
{"id":14,"expanded":false,"name":"クエスト","order":13,"parentId":0,"scrollX":609,"scrollY":452.25},
{"id":15,"expanded":true,"name":"モンスターの研究所","order":53,"parentId":17,"scrollX":523.5555555555555,"scrollY":553.3333333333334},
{"id":16,"expanded":false,"name":"リリス・セーブ","order":51,"parentId":18,"scrollX":593.25,"scrollY":452.25},
{"id":17,"expanded":false,"name":"リリスの部屋","order":52,"parentId":16,"scrollX":736.5,"scrollY":510},
{"id":18,"expanded":false,"name":"共有施設","order":50,"parentId":0,"scrollX":553.5,"scrollY":365.25},
{"id":19,"expanded":false,"name":"モンスターの研究所２","order":54,"parentId":15,"scrollX":485.3333333333333,"scrollY":349.77777777777777},
{"id":20,"expanded":false,"name":"企業クエスト","order":14,"parentId":14,"scrollX":436.44444444444446,"scrollY":268},
{"id":21,"expanded":false,"name":"傭兵ギルドクエスト","order":17,"parentId":14,"scrollX":451.5,"scrollY":440.25},
{"id":22,"expanded":true,"name":"魔法ギルドクエスト","order":18,"parentId":14,"scrollX":0,"scrollY":0},
{"id":23,"expanded":false,"name":"盗賊ギルドクエスト","order":20,"parentId":14,"scrollX":0,"scrollY":0},
{"id":24,"expanded":true,"name":"セーブエリア","order":55,"parentId":16,"scrollX":593.25,"scrollY":459.75},
{"id":25,"expanded":false,"name":"空","order":56,"parentId":24,"scrollX":10604.25,"scrollY":452.25},
{"id":26,"expanded":false,"name":"第一節：小さな悪戯","order":16,"parentId":27,"scrollX":969,"scrollY":915.75},
{"id":27,"expanded":true,"name":"1章","order":15,"parentId":20,"scrollX":436.44444444444446,"scrollY":301.77777777777777},
{"id":28,"expanded":false,"name":"異端審問会裁判所","order":57,"parentId":18,"scrollX":738,"scrollY":452.25},
{"id":29,"expanded":true,"name":"ポーランド東区","order":23,"parentId":44,"scrollX":442.79999999999995,"scrollY":301.8},
{"id":30,"expanded":true,"name":"ポーラの監獄","order":25,"parentId":32,"scrollX":1387.5,"scrollY":378.75},
{"id":31,"expanded":false,"name":"監獄地下","order":26,"parentId":30,"scrollX":1562.3999999999999,"scrollY":683.4},
{"id":32,"expanded":true,"name":"ポーラ領主の館","order":24,"parentId":29,"scrollX":606,"scrollY":454.2},
{"id":33,"expanded":true,"name":"タイトル","order":2,"parentId":11,"scrollX":442.79999999999995,"scrollY":322.2},
{"id":34,"expanded":true,"name":"1章","order":4,"parentId":33,"scrollX":442.79999999999995,"scrollY":322.2},
{"id":35,"expanded":false,"name":"2章","order":5,"parentId":33,"scrollX":736.5,"scrollY":440.25},
{"id":36,"expanded":true,"name":"ワールドマップ","order":21,"parentId":0,"scrollX":1506,"scrollY":4014.6},
{"id":37,"expanded":false,"name":"街の施設","order":58,"parentId":18,"scrollX":553.5,"scrollY":377.25},
{"id":38,"expanded":true,"name":"教会","order":27,"parentId":29,"scrollX":593.25,"scrollY":530.25},
{"id":39,"expanded":false,"name":"盗賊ギルド（支部）","order":59,"parentId":37,"scrollX":553.5,"scrollY":365.25},
{"id":40,"expanded":false,"name":"傭兵ギルド1F","order":60,"parentId":37,"scrollX":565.5,"scrollY":495.75},
{"id":41,"expanded":false,"name":"傭兵ギルド2F","order":61,"parentId":40,"scrollX":593.25,"scrollY":459.75},
{"id":42,"expanded":false,"name":"宿屋","order":62,"parentId":37,"scrollX":594,"scrollY":582.75},
{"id":43,"expanded":false,"name":"武器屋","order":63,"parentId":37,"scrollX":553.5,"scrollY":377.25},
{"id":44,"expanded":true,"name":"ポーランド","order":22,"parentId":36,"scrollX":442.79999999999995,"scrollY":322.2},
{"id":45,"expanded":false,"name":"ポーランド西区","order":28,"parentId":44,"scrollX":442.79999999999995,"scrollY":462.59999999999997},
{"id":46,"expanded":false,"name":"メインクエストリザルト","order":8,"parentId":13,"scrollX":0,"scrollY":0},
{"id":47,"expanded":false,"name":"傭兵ギルドリザルト","order":9,"parentId":13,"scrollX":0,"scrollY":0},
{"id":48,"expanded":false,"name":"魔法ギルドリザルト","order":10,"parentId":13,"scrollX":0,"scrollY":0},
{"id":49,"expanded":false,"name":"盗賊ギルドリザルト","order":11,"parentId":13,"scrollX":609,"scrollY":440.25},
{"id":50,"expanded":false,"name":"酒場クエストリザルト","order":12,"parentId":13,"scrollX":736.5,"scrollY":440.25},
{"id":51,"expanded":false,"name":"呪いの館１","order":19,"parentId":22,"scrollX":609,"scrollY":747.75},
{"id":52,"expanded":true,"name":"メフィストのイベント用","order":39,"parentId":10,"scrollX":832.8,"scrollY":1174.2},
{"id":53,"expanded":false,"name":"魔法屋","order":29,"parentId":45,"scrollX":605.25,"scrollY":453.75},
{"id":54,"expanded":true,"name":"フランス","order":42,"parentId":55,"scrollX":553.5,"scrollY":365.25},
{"id":55,"expanded":false,"name":"フランス","order":41,"parentId":36,"scrollX":816,"scrollY":624},
{"id":56,"expanded":true,"name":"フランス港","order":44,"parentId":55,"scrollX":1126.5,"scrollY":1052.25},
{"id":57,"expanded":false,"name":"フランス城","order":45,"parentId":55,"scrollX":1044,"scrollY":1781.25},
{"id":58,"expanded":false,"name":"城1F","order":47,"parentId":57,"scrollX":1012.5,"scrollY":1152.75},
{"id":59,"expanded":false,"name":"城2F","order":48,"parentId":57,"scrollX":553.5,"scrollY":624.75},
{"id":60,"expanded":false,"name":"城3F","order":49,"parentId":57,"scrollX":780,"scrollY":1091.25},
{"id":61,"expanded":false,"name":"離れの部屋","order":46,"parentId":57,"scrollX":553.5,"scrollY":834.75},
{"id":62,"expanded":false,"name":"道具屋","order":64,"parentId":37,"scrollX":553.5,"scrollY":438.75},
{"id":63,"expanded":false,"name":"魔法屋","order":43,"parentId":54,"scrollX":553.5,"scrollY":377.25},
{"id":64,"expanded":false,"name":"教会","order":65,"parentId":37,"scrollX":553.5,"scrollY":377.25},
{"id":65,"expanded":false,"name":"オープニング","order":3,"parentId":33,"scrollX":442.79999999999995,"scrollY":301.8}
]